boytacean/__init__.py
boytacean/boytacean.cpython-312-darwin.so
boytacean/boytacean.pyi
boytacean/gb.py
boytacean/graphics.py
boytacean/palettes.py
boytacean/pyboy.py
boytacean/video.py
boytacean-0.9.18.dist-info/LICENSE
boytacean-0.9.18.dist-info/METADATA
boytacean-0.9.18.dist-info/WHEEL
boytacean-0.9.18.dist-info/top_level.txt
boytacean-0.9.18.dist-info/RECORD
