Metadata-Version: 2.1
Name: boytacean
Version: 0.9.18
Summary: A Game Boy emulator that is written in Rust
Home-page: https://boytacean.joao.me
Author: João Magalhães
Author-email: joamag@gmail.com
License: Apache License, Version 2.0
Keywords: gameboy emulator rust
Classifier: Development Status :: 5 - Production/Stable
Classifier: Topic :: Utilities
Classifier: License :: OSI Approved :: Apache Software License
Classifier: Operating System :: OS Independent
Classifier: Programming Language :: Python
Classifier: Programming Language :: Python :: 3.5
Classifier: Programming Language :: Python :: 3.6
Classifier: Programming Language :: Python :: 3.7
Classifier: Programming Language :: Python :: 3.8
Classifier: Programming Language :: Python :: 3.9
Classifier: Programming Language :: Python :: 3.10
Classifier: Programming Language :: Python :: 3.11
License-File: LICENSE
